hanbin_hello/__init__.py
hanbin_hello/main.py
hanbin_hello-0.2.0.dist-info/METADATA
hanbin_hello-0.2.0.dist-info/WHEEL
hanbin_hello-0.2.0.dist-info/entry_points.txt
hanbin_hello-0.2.0.dist-info/top_level.txt
hanbin_hello-0.2.0.dist-info/RECORD
