Metadata-Version: 2.1
Name: hanbin-hello
Version: 0.2.0
